23b1060_lab1/23b1060_bcd_to_7_segment_struct.v
module A(input x, input y, input z, input w, output oa);
    wire p,q;
    not (nx, x);
    not (ny, y);
    not (nw, w);
    not (nz, z);
    or (p,x,ny,w);
    or (q,x,y,z,nw);
    and (oa,p,q);

endmodule

module B(input x, input y, input z, input w, output ob);
    wire nx, ny, nw, nz;
    wire p, q;
    not (nx, x);
    not (ny, y);
    not (nw, w);
    not (nz, z);
    or (p, x, ny, z, nw);
    or (q, x, ny, nz, w);
    and (ob, p, q);
endmodule

module C(input x, input y, input z, input w, output oc);
    wire nx, ny, nw, nz;
    not (nx, x);
    not (ny, y);
    not (nw, w);
    not (nz, z);
    or (oc, x, y, nz, w);
endmodule

module D(input x, input y, input z, input w, output od);
    wire nx, ny, nw, nz;
    wire l, m, n;
    not (nx, x);
    not (ny, y);
    not (nw, w);
    not (nz, z);
    or (l, x, ny, z, w);
    or (m, y, z, nw);
    or (n, x, ny, nz, nw);
    and (od, l, m, n);
endmodule

module E(input x, input y, input z, input w, output oe);
    wire nx, ny, nw, nz;
    wire m, n;
    not (nx, x);
    not (ny, y);
    not (nw, w);
    not (nz, z);
    and (m, nx, z, nw);
    and (n, ny, nz, nw);
    or (oe, m, n);
endmodule

module F(input x, input y, input z, input w, output of);
    wire nx, ny, nw, nz;
    wire p, q, r;
    not (nx, x);
    not (ny, y);
    not (nw, w);
    not (nz, z);
    or (p, x, y, nw);
    or (q, x, y, nz);
    or (r, x, nz, nw);
    and (of, p, q, r);
endmodule

module G(input x, input y, input z, input w, output og);
    wire nx, ny, nw, nz;
    wire c, d;
    not (nx, x);
    not (ny, y);
    not (nw, w);
    not (nz, z);
    or (c, x, y, z);
    or (d, x, ny, nz, nw);
    and (og, c, d);
endmodule

lab1/23b1060_tb_bcd_to_7_segment_struct.v
module testbench;
reg x,y,z,w;
integer i,j,k,l;
wire oa,ob,oc,od,oe,of,og;
A a_instance(.oa(oa), .x(x),.y(y),.z(z), .w(w));
B b_instance(.ob(ob), .x(x),.y(y),.z(z), .w(w));
C c_instance(.oc(oc), .x(x),.y(y),.z(z), .w(w));
D d_instance(.od(od), .x(x),.y(y),.z(z), .w(w));
E e_instance(.oe(oe), .x(x),.y(y),.z(z), .w(w));
F f_instance(.of(of), .x(x),.y(y),.z(z), .w(w));
G g_instance(.og(og), .x(x),.y(y),.z(z), .w(w));
initial begin
$dumpvars();
$display("23b1060: Madhav R Babu");
$monitor("x: %b y:%b z:%b w:%b A:%b B:%b C:%b D:%b E:%b F:%b G:%b", x, y,z,w,oa,ob,oc,od,oe,of,og);
x=0; y=0; z=0; w=0; #1;
for(i=0; i<1; i=i+1) begin
    for(j=0; j<2; j=j+1) begin
        for(k=0; k<2; k=k+1) begin
            for(l=0; l<2; l=l+1) begin
                x=i; y=j; z=k; w=l;
                #1;
                end
            end
        end
    end
x=1; y=0; z=0; w=0; #1;
x=1; y=0; z=0; w=1; #1;
end
endmodule

lab1/dump.vcd
$date
	Thu Aug  8 15:57:06 2024
$end
$version
	Icarus Verilog
$end
$timescale
	1s
$end
$scope module testbench $end
$var wire 1 ! og $end
$var wire 1 " of $end
$var wire 1 # oe $end
$var wire 1 $ od $end
$var wire 1 % oc $end
$var wire 1 & ob $end
$var wire 1 ' oa $end
$var reg 1 ( w $end
$var reg 1 ) x $end
$var reg 1 * y $end
$var reg 1 + z $end
$var integer 32 , i [31:0] $end
$var integer 32 - j [31:0] $end
$var integer 32 . k [31:0] $end
$var integer 32 / l [31:0] $end
$scope module a_instance $end
$var wire 1 0 nw $end
$var wire 1 1 nx $end
$var wire 1 2 ny $end
$var wire 1 3 nz $end
$var wire 1 ' oa $end
$var wire 1 4 p $end
$var wire 1 5 q $end
$var wire 1 ( w $end
$var wire 1 ) x $end
$var wire 1 * y $end
$var wire 1 + z $end
$upscope $end
$scope module b_instance $end
$var wire 1 6 nw $end
$var wire 1 7 nx $end
$var wire 1 8 ny $end
$var wire 1 9 nz $end
$var wire 1 & ob $end
$var wire 1 : p $end
$var wire 1 ; q $end
$var wire 1 ( w $end
$var wire 1 ) x $end
$var wire 1 * y $end
$var wire 1 + z $end
$upscope $end
$scope module c_instance $end
$var wire 1 < nw $end
$var wire 1 = nx $end
$var wire 1 > ny $end
$var wire 1 ? nz $end
$var wire 1 % oc $end
$var wire 1 ( w $end
$var wire 1 ) x $end
$var wire 1 * y $end
$var wire 1 + z $end
$upscope $end
$scope module d_instance $end
$var wire 1 @ l $end
$var wire 1 A m $end
$var wire 1 B n $end
$var wire 1 C nw $end
$var wire 1 D nx $end
$var wire 1 E ny $end
$var wire 1 F nz $end
$var wire 1 $ od $end
$var wire 1 ( w $end
$var wire 1 ) x $end
$var wire 1 * y $end
$var wire 1 + z $end
$upscope $end
$scope module e_instance $end
$var wire 1 G m $end
$var wire 1 H n $end
$var wire 1 I nw $end
$var wire 1 J nx $end
$var wire 1 K ny $end
$var wire 1 L nz $end
$var wire 1 # oe $end
$var wire 1 ( w $end
$var wire 1 ) x $end
$var wire 1 * y $end
$var wire 1 + z $end
$upscope $end
$scope module f_instance $end
$var wire 1 M nw $end
$var wire 1 N nx $end
$var wire 1 O ny $end
$var wire 1 P nz $end
$var wire 1 " of $end
$var wire 1 Q p $end
$var wire 1 R q $end
$var wire 1 S r $end
$var wire 1 ( w $end
$var wire 1 ) x $end
$var wire 1 * y $end
$var wire 1 + z $end
$upscope $end
$scope module g_instance $end
$var wire 1 T c $end
$var wire 1 U d $end
$var wire 1 V nw $end
$var wire 1 W nx $end
$var wire 1 X ny $end
$var wire 1 Y nz $end
$var wire 1 ! og $end
$var wire 1 ( w $end
$var wire 1 ) x $end
$var wire 1 * y $end
$var wire 1 + z $end
$upscope $end
$upscope $end
$enddefinitions $end
#0
$dumpvars
1Y
1X
1W
1V
1U
0T
1S
1R
1Q
1P
1O
1N
1M
1L
1K
1J
1I
1H
0G
1F
1E
1D
1C
1B
1A
1@
1?
1>
1=
1<
1;
1:
19
18
17
16
15
14
13
12
11
10
bx /
bx .
bx -
bx ,
0+
0*
0)
0(
1'
1&
1%
1$
1#
1"
0!
$end
#1
b0 /
b0 .
b0 -
b0 ,
#2
0'
0$
0#
0"
05
0A
0H
0Q
00
06
0<
0C
0I
0M
0V
1(
b1 /
#3
1#
1G
1Q
1'
1$
0R
1!
10
16
1<
0%
1C
1I
1M
1V
03
15
09
0?
0F
1A
0L
0P
0Y
1T
0(
1+
b1 .
b0 /
#4
0#
0G
0Q
0S
00
06
0<
1%
0C
0I
0M
0V
1(
b1 /
#5
1"
0'
1&
0$
1S
10
04
16
1<
1C
1I
1M
1V
13
19
1:
1?
1F
0@
1L
1P
1Y
02
08
0>
0E
0K
0O
1Q
1R
0X
0(
0+
1*
b1 -
b0 .
b0 /
#6
0&
1'
0:
1$
00
14
06
0<
0C
1@
0I
0M
0V
1(
b1 /
#7
1#
0'
1G
10
04
16
0;
1<
1C
1I
1M
1V
03
09
1:
0?
0F
0L
0P
0Y
0(
1+
b1 .
b0 /
#8
0$
0#
0"
0!
1'
1&
0B
0G
0S
0U
00
14
06
1;
0<
0C
0I
0M
0V
1(
b1 /
#9
1$
1#
1H
1"
1!
10
16
1<
1C
1I
1M
1V
13
19
1?
1F
1L
1P
1Y
12
18
1>
1E
1A
1K
1O
1X
01
07
0=
0D
1B
0J
0N
1S
0W
1U
0(
0+
0*
1)
b1 ,
b10 -
b10 .
b10 /
#10
0$
0#
0A
0H
00
06
0<
0C
0I
0M
0V
1(
